[
  {
    "symbol":"BTC\/EUR",
    "direction":"Long",
    "indicator":"jma",
    "htf":"8h",
    "param_desc":"ParamA=30.0, ParamB=0.0, ATR=None",
    "entry_time":"2025-11-29T12:00:00+01:00",
    "entry_price":78238.83,
    "exit_time":"2025-12-01T12:00:00+01:00",
    "exit_price":74130.44,
    "stake":1000.0,
    "fees":2.0,
    "pnl":-54.5108823841,
    "equity_after":13945.4891176159,
    "reason":"Trend flip",
    "size_units":0.0127813772,
    "Zeit":"2025-11-29T12:00:00+01:00",
    "ExitZeit":"2025-12-01T12:00:00+01:00",
    "Entry":78238.83,
    "ExitPreis":74130.44
  },
  {
    "symbol":"BTC\/EUR",
    "direction":"Long",
    "indicator":"jma",
    "htf":"8h",
    "param_desc":"ParamA=30.0, ParamB=0.0, ATR=None",
    "entry_time":"2025-12-02T11:00:00+01:00",
    "entry_price":75241.24,
    "exit_time":"2025-12-04T11:00:00+01:00",
    "exit_price":79923.18,
    "stake":1000.0,
    "fees":2.0,
    "pnl":60.2257155783,
    "equity_after":14005.7148331942,
    "reason":"Trend flip",
    "size_units":0.0132905837,
    "Zeit":"2025-12-02T11:00:00+01:00",
    "ExitZeit":"2025-12-04T11:00:00+01:00",
    "Entry":75241.24,
    "ExitPreis":79923.18
  },
  {
    "symbol":"BTC\/EUR",
    "direction":"Long",
    "indicator":"jma",
    "htf":"8h",
    "param_desc":"ParamA=30.0, ParamB=0.0, ATR=None",
    "entry_time":"2025-12-04T16:00:00+01:00",
    "entry_price":79739.86,
    "exit_time":"2025-12-06T16:00:00+01:00",
    "exit_price":77158.86,
    "stake":1000.0,
    "fees":2.0,
    "pnl":-34.367751837,
    "equity_after":13971.3470813572,
    "reason":"Trend flip",
    "size_units":0.0125407795,
    "Zeit":"2025-12-04T16:00:00+01:00",
    "ExitZeit":"2025-12-06T16:00:00+01:00",
    "Entry":79739.86,
    "ExitPreis":77158.86
  },
  {
    "symbol":"BTC\/EUR",
    "direction":"Long",
    "indicator":"jma",
    "htf":"8h",
    "param_desc":"ParamA=30.0, ParamB=0.0, ATR=None",
    "entry_time":"2025-12-08T02:00:00+01:00",
    "entry_price":78100.7,
    "exit_time":"2025-12-10T08:00:00+01:00",
    "exit_price":79583.8,
    "stake":1000.0,
    "fees":2.0,
    "pnl":16.989586521,
    "equity_after":13988.3366678782,
    "reason":"Trend flip",
    "size_units":0.0128039826,
    "Zeit":"2025-12-08T02:00:00+01:00",
    "ExitZeit":"2025-12-10T08:00:00+01:00",
    "Entry":78100.7,
    "ExitPreis":79583.8
  },
  {
    "symbol":"BTC\/EUR",
    "direction":"Long",
    "indicator":"jma",
    "htf":"8h",
    "param_desc":"ParamA=30.0, ParamB=0.0, ATR=None",
    "entry_time":"2025-12-10T10:00:00+01:00",
    "entry_price":79865.11,
    "exit_time":"2025-12-12T12:00:00+01:00",
    "exit_price":78790.8,
    "stake":1000.0,
    "fees":2.0,
    "pnl":-15.4515560049,
    "equity_after":13972.8851118733,
    "reason":"Trend flip",
    "size_units":0.0125211122,
    "Zeit":"2025-12-10T10:00:00+01:00",
    "ExitZeit":"2025-12-12T12:00:00+01:00",
    "Entry":79865.11,
    "ExitPreis":78790.8
  },
  {
    "symbol":"BTC\/EUR",
    "direction":"Long",
    "indicator":"jma",
    "htf":"8h",
    "param_desc":"ParamA=30.0, ParamB=0.0, ATR=None",
    "entry_time":"2025-12-15T01:00:00+01:00",
    "entry_price":75470.57,
    "exit_time":"2025-12-17T01:00:00+01:00",
    "exit_price":74448.38,
    "stake":1000.0,
    "fees":2.0,
    "pnl":-15.5442199522,
    "equity_after":13957.3408919211,
    "reason":"Trend flip",
    "size_units":0.0132501981,
    "Zeit":"2025-12-15T01:00:00+01:00",
    "ExitZeit":"2025-12-17T01:00:00+01:00",
    "Entry":75470.57,
    "ExitPreis":74448.38
  },
  {
    "symbol":"BTC\/EUR",
    "direction":"Long",
    "indicator":"jma",
    "htf":"8h",
    "param_desc":"ParamA=30.0, ParamB=0.0, ATR=None",
    "entry_time":"2025-12-18T03:00:00+01:00",
    "entry_price":73785.87,
    "exit_time":"2025-12-20T08:00:00+01:00",
    "exit_price":75339.35,
    "stake":1000.0,
    "fees":2.0,
    "pnl":19.0538955494,
    "equity_after":13976.3947874704,
    "reason":"Trend flip",
    "size_units":0.0135527304,
    "Zeit":"2025-12-18T03:00:00+01:00",
    "ExitZeit":"2025-12-20T08:00:00+01:00",
    "Entry":73785.87,
    "ExitPreis":75339.35
  },
  {
    "symbol":"BTC\/EUR",
    "direction":"Long",
    "indicator":"jma",
    "htf":"8h",
    "param_desc":"ParamA=30.0, ParamB=0.0, ATR=None",
    "entry_time":"2025-12-20T09:00:00+01:00",
    "entry_price":75387.26,
    "exit_time":"2025-12-22T14:00:00+01:00",
    "exit_price":76514.01,
    "stake":1000.0,
    "fees":2.0,
    "pnl":12.9461593378,
    "equity_after":13989.3409468082,
    "reason":"Trend flip",
    "size_units":0.0132648408,
    "Zeit":"2025-12-20T09:00:00+01:00",
    "ExitZeit":"2025-12-22T14:00:00+01:00",
    "Entry":75387.26,
    "ExitPreis":76514.01
  },
  {
    "symbol":"BTC\/EUR",
    "direction":"Long",
    "indicator":"jma",
    "htf":"8h",
    "param_desc":"ParamA=30.0, ParamB=0.0, ATR=None",
    "entry_time":"2025-12-22T15:00:00+01:00",
    "entry_price":76632.63,
    "exit_time":"2025-12-24T15:00:00+01:00",
    "exit_price":73798.03,
    "stake":1000.0,
    "fees":2.0,
    "pnl":-38.9894651926,
    "equity_after":13950.3514816157,
    "reason":"Trend flip",
    "size_units":0.0130492716,
    "Zeit":"2025-12-22T15:00:00+01:00",
    "ExitZeit":"2025-12-24T15:00:00+01:00",
    "Entry":76632.63,
    "ExitPreis":73798.03
  },
  {
    "symbol":"BTC\/EUR",
    "direction":"Long",
    "indicator":"jma",
    "htf":"8h",
    "param_desc":"ParamA=30.0, ParamB=0.0, ATR=None",
    "entry_time":"2025-12-25T02:00:00+01:00",
    "entry_price":74427.16,
    "exit_time":"2025-12-27T11:00:00+01:00",
    "exit_price":74277.87,
    "stake":1000.0,
    "fees":2.0,
    "pnl":-4.005853777,
    "equity_after":13946.3456278386,
    "reason":"Trend flip",
    "size_units":0.0134359554,
    "Zeit":"2025-12-25T02:00:00+01:00",
    "ExitZeit":"2025-12-27T11:00:00+01:00",
    "Entry":74427.16,
    "ExitPreis":74277.87
  },
  {
    "symbol":"ETH\/EUR",
    "direction":"Long",
    "indicator":"jma",
    "htf":"12h",
    "param_desc":"ParamA=30.0, ParamB=0.0, ATR=1.5",
    "entry_time":"2025-12-02T23:00:00+01:00",
    "entry_price":2593.72,
    "exit_time":"2025-12-05T00:00:00+01:00",
    "exit_price":2693.21,
    "stake":1000.0,
    "fees":2.0,
    "pnl":36.3580340206,
    "equity_after":13982.7036618593,
    "reason":"Trend flip",
    "size_units":0.385546628,
    "Zeit":"2025-12-02T23:00:00+01:00",
    "ExitZeit":"2025-12-05T00:00:00+01:00",
    "Entry":2593.72,
    "ExitPreis":2693.21
  },
  {
    "symbol":"ETH\/EUR",
    "direction":"Long",
    "indicator":"jma",
    "htf":"12h",
    "param_desc":"ParamA=30.0, ParamB=0.0, ATR=1.5",
    "entry_time":"2025-12-05T01:00:00+01:00",
    "entry_price":2702.53,
    "exit_time":"2025-12-05T14:00:00+01:00",
    "exit_price":2661.2034256305,
    "stake":1000.0,
    "fees":2.0,
    "pnl":-17.2918096633,
    "equity_after":13965.4118521959,
    "reason":"ATR stop x1.50",
    "size_units":0.3700236445,
    "Zeit":"2025-12-05T01:00:00+01:00",
    "ExitZeit":"2025-12-05T14:00:00+01:00",
    "Entry":2702.53,
    "ExitPreis":2661.2034256305
  },
  {
    "symbol":"ETH\/EUR",
    "direction":"Long",
    "indicator":"jma",
    "htf":"12h",
    "param_desc":"ParamA=30.0, ParamB=0.0, ATR=1.5",
    "entry_time":"2025-12-07T13:00:00+01:00",
    "entry_price":2619.95,
    "exit_time":"2025-12-07T15:00:00+01:00",
    "exit_price":2603.5097190404,
    "stake":1000.0,
    "fees":2.0,
    "pnl":-8.2750361494,
    "equity_after":13957.1368160465,
    "reason":"ATR stop x1.50",
    "size_units":0.3816866734,
    "Zeit":"2025-12-07T13:00:00+01:00",
    "ExitZeit":"2025-12-07T15:00:00+01:00",
    "Entry":2619.95,
    "ExitPreis":2603.5097190404
  },
  {
    "symbol":"ETH\/EUR",
    "direction":"Long",
    "indicator":"jma",
    "htf":"12h",
    "param_desc":"ParamA=30.0, ParamB=0.0, ATR=1.5",
    "entry_time":"2025-12-07T16:00:00+01:00",
    "entry_price":2606.78,
    "exit_time":"2025-12-09T21:00:00+01:00",
    "exit_price":2856.27,
    "stake":1000.0,
    "fees":2.0,
    "pnl":93.7081149924,
    "equity_after":14050.844931039,
    "reason":"Trend flip",
    "size_units":0.3836150346,
    "Zeit":"2025-12-07T16:00:00+01:00",
    "ExitZeit":"2025-12-09T21:00:00+01:00",
    "Entry":2606.78,
    "ExitPreis":2856.27
  },
  {
    "symbol":"ETH\/EUR",
    "direction":"Long",
    "indicator":"jma",
    "htf":"12h",
    "param_desc":"ParamA=30.0, ParamB=0.0, ATR=1.5",
    "entry_time":"2025-12-09T23:00:00+01:00",
    "entry_price":2862.19,
    "exit_time":"2025-12-11T01:00:00+01:00",
    "exit_price":2812.0841963874,
    "stake":1000.0,
    "fees":2.0,
    "pnl":-19.5061067269,
    "equity_after":14031.3388243121,
    "reason":"ATR stop x1.50",
    "size_units":0.3493828153,
    "Zeit":"2025-12-09T23:00:00+01:00",
    "ExitZeit":"2025-12-11T01:00:00+01:00",
    "Entry":2862.19,
    "ExitPreis":2812.0841963874
  },
  {
    "symbol":"ETH\/EUR",
    "direction":"Long",
    "indicator":"jma",
    "htf":"12h",
    "param_desc":"ParamA=30.0, ParamB=0.0, ATR=1.5",
    "entry_time":"2025-12-15T01:00:00+01:00",
    "entry_price":2624.47,
    "exit_time":"2025-12-15T15:00:00+01:00",
    "exit_price":2596.7139399955,
    "stake":1000.0,
    "fees":2.0,
    "pnl":-12.5758724636,
    "equity_after":14018.7629518485,
    "reason":"ATR stop x1.50",
    "size_units":0.3810293126,
    "Zeit":"2025-12-15T01:00:00+01:00",
    "ExitZeit":"2025-12-15T15:00:00+01:00",
    "Entry":2624.47,
    "ExitPreis":2596.7139399955
  },
  {
    "symbol":"ETH\/EUR",
    "direction":"Long",
    "indicator":"jma",
    "htf":"12h",
    "param_desc":"ParamA=30.0, ParamB=0.0, ATR=1.5",
    "entry_time":"2025-12-19T03:00:00+01:00",
    "entry_price":2417.96,
    "exit_time":"2025-12-21T13:00:00+01:00",
    "exit_price":2552.6,
    "stake":1000.0,
    "fees":2.0,
    "pnl":53.6833032805,
    "equity_after":14072.446255129,
    "reason":"Trend flip",
    "size_units":0.4135717712,
    "Zeit":"2025-12-19T03:00:00+01:00",
    "ExitZeit":"2025-12-21T13:00:00+01:00",
    "Entry":2417.96,
    "ExitPreis":2552.6
  },
  {
    "symbol":"ETH\/EUR",
    "direction":"Long",
    "indicator":"jma",
    "htf":"12h",
    "param_desc":"ParamA=30.0, ParamB=0.0, ATR=1.5",
    "entry_time":"2025-12-21T17:00:00+01:00",
    "entry_price":2548.7,
    "exit_time":"2025-12-22T21:00:00+01:00",
    "exit_price":2528.7456176908,
    "stake":1000.0,
    "fees":2.0,
    "pnl":-9.8292393413,
    "equity_after":14062.6170157877,
    "reason":"ATR stop x1.50",
    "size_units":0.3923568878,
    "Zeit":"2025-12-21T17:00:00+01:00",
    "ExitZeit":"2025-12-22T21:00:00+01:00",
    "Entry":2548.7,
    "ExitPreis":2528.7456176908
  },
  {
    "symbol":"ETH\/EUR",
    "direction":"Long",
    "indicator":"jma",
    "htf":"12h",
    "param_desc":"ParamA=30.0, ParamB=0.0, ATR=1.5",
    "entry_time":"2025-12-22T23:00:00+01:00",
    "entry_price":2559.39,
    "exit_time":"2025-12-23T04:00:00+01:00",
    "exit_price":2528.5069842639,
    "stake":1000.0,
    "fees":2.0,
    "pnl":-14.0665532553,
    "equity_after":14048.5504625324,
    "reason":"ATR stop x1.50",
    "size_units":0.3907181008,
    "Zeit":"2025-12-22T23:00:00+01:00",
    "ExitZeit":"2025-12-23T04:00:00+01:00",
    "Entry":2559.39,
    "ExitPreis":2528.5069842639
  },
  {
    "symbol":"ETH\/EUR",
    "direction":"Long",
    "indicator":"jma",
    "htf":"12h",
    "param_desc":"ParamA=30.0, ParamB=0.0, ATR=1.5",
    "entry_time":"2025-12-26T03:00:00+01:00",
    "entry_price":2518.04,
    "exit_time":"2025-12-26T15:00:00+01:00",
    "exit_price":2491.7319469487,
    "stake":1000.0,
    "fees":2.0,
    "pnl":-12.4478296815,
    "equity_after":14036.1026328508,
    "reason":"ATR stop x1.50",
    "size_units":0.397134279,
    "Zeit":"2025-12-26T03:00:00+01:00",
    "ExitZeit":"2025-12-26T15:00:00+01:00",
    "Entry":2518.04,
    "ExitPreis":2491.7319469487
  },
  {
    "symbol":"LINK\/EUR",
    "direction":"Long",
    "indicator":"jma",
    "htf":"1h",
    "param_desc":"ParamA=30.0, ParamB=0.0, ATR=1.5",
    "entry_time":"2025-12-08T23:00:00+01:00",
    "entry_price":11.96,
    "exit_time":"2025-12-09T04:00:00+01:00",
    "exit_price":11.9371561432,
    "stake":1000.0,
    "fees":2.0,
    "pnl":-3.9100214701,
    "equity_after":14032.1926113808,
    "reason":"ATR stop x1.50",
    "size_units":83.6120401338,
    "Zeit":"2025-12-08T23:00:00+01:00",
    "ExitZeit":"2025-12-09T04:00:00+01:00",
    "Entry":11.96,
    "ExitPreis":11.9371561432
  },
  {
    "symbol":"LINK\/EUR",
    "direction":"Long",
    "indicator":"jma",
    "htf":"1h",
    "param_desc":"ParamA=30.0, ParamB=0.0, ATR=1.5",
    "entry_time":"2025-12-09T12:00:00+01:00",
    "entry_price":11.77,
    "exit_time":"2025-12-11T03:00:00+01:00",
    "exit_price":11.7482540493,
    "stake":1000.0,
    "fees":2.0,
    "pnl":-3.8475743993,
    "equity_after":14028.3450369815,
    "reason":"ATR stop x1.50",
    "size_units":84.9617672048,
    "Zeit":"2025-12-09T12:00:00+01:00",
    "ExitZeit":"2025-12-11T03:00:00+01:00",
    "Entry":11.77,
    "ExitPreis":11.7482540493
  },
  {
    "symbol":"LINK\/EUR",
    "direction":"Long",
    "indicator":"jma",
    "htf":"1h",
    "param_desc":"ParamA=30.0, ParamB=0.0, ATR=1.5",
    "entry_time":"2025-12-11T10:00:00+01:00",
    "entry_price":11.61,
    "exit_time":"2025-12-12T17:00:00+01:00",
    "exit_price":11.4283920863,
    "stake":1000.0,
    "fees":2.0,
    "pnl":-17.642369828,
    "equity_after":14010.7026671535,
    "reason":"ATR stop x1.50",
    "size_units":86.1326442722,
    "Zeit":"2025-12-11T10:00:00+01:00",
    "ExitZeit":"2025-12-12T17:00:00+01:00",
    "Entry":11.61,
    "ExitPreis":11.4283920863
  },
  {
    "symbol":"LINK\/EUR",
    "direction":"Long",
    "indicator":"jma",
    "htf":"1h",
    "param_desc":"ParamA=30.0, ParamB=0.0, ATR=1.5",
    "entry_time":"2025-12-12T23:00:00+01:00",
    "entry_price":11.64,
    "exit_time":"2025-12-14T18:00:00+01:00",
    "exit_price":11.4468649857,
    "stake":1000.0,
    "fees":2.0,
    "pnl":-18.5923551845,
    "equity_after":13992.110311969,
    "reason":"ATR stop x1.50",
    "size_units":85.910652921,
    "Zeit":"2025-12-12T23:00:00+01:00",
    "ExitZeit":"2025-12-14T18:00:00+01:00",
    "Entry":11.64,
    "ExitPreis":11.4468649857
  },
  {
    "symbol":"LINK\/EUR",
    "direction":"Long",
    "indicator":"jma",
    "htf":"1h",
    "param_desc":"ParamA=30.0, ParamB=0.0, ATR=1.5",
    "entry_time":"2025-12-15T01:00:00+01:00",
    "entry_price":11.41,
    "exit_time":"2025-12-15T15:00:00+01:00",
    "exit_price":11.2832990737,
    "stake":1000.0,
    "fees":2.0,
    "pnl":-13.1043756634,
    "equity_after":13979.0059363056,
    "reason":"ATR stop x1.50",
    "size_units":87.6424189308,
    "Zeit":"2025-12-15T01:00:00+01:00",
    "ExitZeit":"2025-12-15T15:00:00+01:00",
    "Entry":11.41,
    "ExitPreis":11.2832990737
  },
  {
    "symbol":"LINK\/EUR",
    "direction":"Long",
    "indicator":"jma",
    "htf":"1h",
    "param_desc":"ParamA=30.0, ParamB=0.0, ATR=1.5",
    "entry_time":"2025-12-15T22:00:00+01:00",
    "entry_price":10.84,
    "exit_time":"2025-12-17T17:00:00+01:00",
    "exit_price":10.6439079433,
    "stake":1000.0,
    "fees":2.0,
    "pnl":-20.0896731315,
    "equity_after":13958.9162631741,
    "reason":"ATR stop x1.50",
    "size_units":92.2509225092,
    "Zeit":"2025-12-15T22:00:00+01:00",
    "ExitZeit":"2025-12-17T17:00:00+01:00",
    "Entry":10.84,
    "ExitPreis":10.6439079433
  },
  {
    "symbol":"LINK\/EUR",
    "direction":"Long",
    "indicator":"jma",
    "htf":"1h",
    "param_desc":"ParamA=30.0, ParamB=0.0, ATR=1.5",
    "entry_time":"2025-12-17T23:00:00+01:00",
    "entry_price":10.46,
    "exit_time":"2025-12-18T18:00:00+01:00",
    "exit_price":10.2564551301,
    "stake":1000.0,
    "fees":2.0,
    "pnl":-21.4593565869,
    "equity_after":13937.4569065872,
    "reason":"ATR stop x1.50",
    "size_units":95.6022944551,
    "Zeit":"2025-12-17T23:00:00+01:00",
    "ExitZeit":"2025-12-18T18:00:00+01:00",
    "Entry":10.46,
    "ExitPreis":10.2564551301
  },
  {
    "symbol":"LINK\/EUR",
    "direction":"Long",
    "indicator":"jma",
    "htf":"1h",
    "param_desc":"ParamA=30.0, ParamB=0.0, ATR=1.5",
    "entry_time":"2025-12-18T22:00:00+01:00",
    "entry_price":10.26,
    "exit_time":"2025-12-20T23:00:00+01:00",
    "exit_price":10.75,
    "stake":1000.0,
    "fees":2.0,
    "pnl":45.7582846004,
    "equity_after":13983.2151911876,
    "reason":"Trend flip",
    "size_units":97.4658869396,
    "Zeit":"2025-12-18T22:00:00+01:00",
    "ExitZeit":"2025-12-20T23:00:00+01:00",
    "Entry":10.26,
    "ExitPreis":10.75
  },
  {
    "symbol":"LINK\/EUR",
    "direction":"Long",
    "indicator":"jma",
    "htf":"1h",
    "param_desc":"ParamA=30.0, ParamB=0.0, ATR=1.5",
    "entry_time":"2025-12-21T05:00:00+01:00",
    "entry_price":10.67,
    "exit_time":"2025-12-21T14:00:00+01:00",
    "exit_price":10.584262041,
    "stake":1000.0,
    "fees":2.0,
    "pnl":-10.0354225861,
    "equity_after":13973.1797686015,
    "reason":"ATR stop x1.50",
    "size_units":93.7207122774,
    "Zeit":"2025-12-21T05:00:00+01:00",
    "ExitZeit":"2025-12-21T14:00:00+01:00",
    "Entry":10.67,
    "ExitPreis":10.584262041
  },
  {
    "symbol":"LINK\/EUR",
    "direction":"Long",
    "indicator":"jma",
    "htf":"1h",
    "param_desc":"ParamA=30.0, ParamB=0.0, ATR=1.5",
    "entry_time":"2025-12-21T20:00:00+01:00",
    "entry_price":10.59,
    "exit_time":"2025-12-23T06:00:00+01:00",
    "exit_price":10.4819385692,
    "stake":1000.0,
    "fees":2.0,
    "pnl":-12.2041011125,
    "equity_after":13960.975667489,
    "reason":"ATR stop x1.50",
    "size_units":94.4287063267,
    "Zeit":"2025-12-21T20:00:00+01:00",
    "ExitZeit":"2025-12-23T06:00:00+01:00",
    "Entry":10.59,
    "ExitPreis":10.4819385692
  },
  {
    "symbol":"LINK\/EUR",
    "direction":"Long",
    "indicator":"jma",
    "htf":"1h",
    "param_desc":"ParamA=30.0, ParamB=0.0, ATR=1.5",
    "entry_time":"2025-12-23T12:00:00+01:00",
    "entry_price":10.48,
    "exit_time":"2025-12-23T14:00:00+01:00",
    "exit_price":10.3595568889,
    "stake":1000.0,
    "fees":2.0,
    "pnl":-13.4926632702,
    "equity_after":13947.4830042188,
    "reason":"ATR stop x1.50",
    "size_units":95.4198473282,
    "Zeit":"2025-12-23T12:00:00+01:00",
    "ExitZeit":"2025-12-23T14:00:00+01:00",
    "Entry":10.48,
    "ExitPreis":10.3595568889
  },
  {
    "symbol":"LINK\/EUR",
    "direction":"Long",
    "indicator":"jma",
    "htf":"1h",
    "param_desc":"ParamA=30.0, ParamB=0.0, ATR=1.5",
    "entry_time":"2025-12-23T16:00:00+01:00",
    "entry_price":10.43,
    "exit_time":"2025-12-24T06:00:00+01:00",
    "exit_price":10.3024817603,
    "stake":1000.0,
    "fees":2.0,
    "pnl":-14.2261015987,
    "equity_after":13933.2569026201,
    "reason":"ATR stop x1.50",
    "size_units":95.8772770853,
    "Zeit":"2025-12-23T16:00:00+01:00",
    "ExitZeit":"2025-12-24T06:00:00+01:00",
    "Entry":10.43,
    "ExitPreis":10.3024817603
  },
  {
    "symbol":"LINK\/EUR",
    "direction":"Long",
    "indicator":"jma",
    "htf":"1h",
    "param_desc":"ParamA=30.0, ParamB=0.0, ATR=1.5",
    "entry_time":"2025-12-24T11:00:00+01:00",
    "entry_price":10.34,
    "exit_time":"2025-12-24T15:00:00+01:00",
    "exit_price":10.2295356799,
    "stake":1000.0,
    "fees":2.0,
    "pnl":-12.6832031014,
    "equity_after":13920.5736995187,
    "reason":"ATR stop x1.50",
    "size_units":96.7117988395,
    "Zeit":"2025-12-24T11:00:00+01:00",
    "ExitZeit":"2025-12-24T15:00:00+01:00",
    "Entry":10.34,
    "ExitPreis":10.2295356799
  },
  {
    "symbol":"LINK\/EUR",
    "direction":"Long",
    "indicator":"jma",
    "htf":"1h",
    "param_desc":"ParamA=30.0, ParamB=0.0, ATR=1.5",
    "entry_time":"2025-12-24T16:00:00+01:00",
    "entry_price":10.34,
    "exit_time":"2025-12-26T00:00:00+01:00",
    "exit_price":10.2213677452,
    "stake":1000.0,
    "fees":2.0,
    "pnl":-13.4731387595,
    "equity_after":13907.1005607592,
    "reason":"ATR stop x1.50",
    "size_units":96.7117988395,
    "Zeit":"2025-12-24T16:00:00+01:00",
    "ExitZeit":"2025-12-26T00:00:00+01:00",
    "Entry":10.34,
    "ExitPreis":10.2213677452
  },
  {
    "symbol":"LINK\/EUR",
    "direction":"Long",
    "indicator":"jma",
    "htf":"1h",
    "param_desc":"ParamA=30.0, ParamB=0.0, ATR=1.5",
    "entry_time":"2025-12-26T02:00:00+01:00",
    "entry_price":10.33,
    "exit_time":"2025-12-28T05:00:00+01:00",
    "exit_price":10.59,
    "stake":1000.0,
    "fees":2.0,
    "pnl":23.1694094869,
    "equity_after":13930.2699702462,
    "reason":"Trend flip",
    "size_units":96.8054211036,
    "Zeit":"2025-12-26T02:00:00+01:00",
    "ExitZeit":"2025-12-28T05:00:00+01:00",
    "Entry":10.33,
    "ExitPreis":10.59
  },
  {
    "symbol":"LUNC\/USDT",
    "direction":"Long",
    "indicator":"jma",
    "htf":"12h",
    "param_desc":"ParamA=30.0, ParamB=0.0, ATR=None",
    "entry_time":"2025-12-02T13:00:00+01:00",
    "entry_price":0.00002792,
    "exit_time":"2025-12-05T23:00:00+01:00",
    "exit_price":0.00005533,
    "stake":1000.0,
    "fees":2.0,
    "pnl":979.7335243553,
    "equity_after":14910.0034946015,
    "reason":"Trend flip",
    "size_units":35816618.9111747816,
    "Zeit":"2025-12-02T13:00:00+01:00",
    "ExitZeit":"2025-12-05T23:00:00+01:00",
    "Entry":0.00002792,
    "ExitPreis":0.00005533
  },
  {
    "symbol":"LUNC\/USDT",
    "direction":"Long",
    "indicator":"jma",
    "htf":"12h",
    "param_desc":"ParamA=30.0, ParamB=0.0, ATR=None",
    "entry_time":"2025-12-06T01:00:00+01:00",
    "entry_price":0.000059,
    "exit_time":"2025-12-08T08:00:00+01:00",
    "exit_price":0.00005242,
    "stake":1000.0,
    "fees":2.0,
    "pnl":-113.5254237288,
    "equity_after":14796.4780708727,
    "reason":"Trend flip",
    "size_units":16949152.5423728824,
    "Zeit":"2025-12-06T01:00:00+01:00",
    "ExitZeit":"2025-12-08T08:00:00+01:00",
    "Entry":0.000059,
    "ExitPreis":0.00005242
  },
  {
    "symbol":"LUNC\/USDT",
    "direction":"Long",
    "indicator":"jma",
    "htf":"12h",
    "param_desc":"ParamA=30.0, ParamB=0.0, ATR=None",
    "entry_time":"2025-12-08T15:00:00+01:00",
    "entry_price":0.00005081,
    "exit_time":"2025-12-10T19:00:00+01:00",
    "exit_price":0.00006345,
    "stake":1000.0,
    "fees":2.0,
    "pnl":246.7699271797,
    "equity_after":15043.2479980523,
    "reason":"Trend flip",
    "size_units":19681165.1249753982,
    "Zeit":"2025-12-08T15:00:00+01:00",
    "ExitZeit":"2025-12-10T19:00:00+01:00",
    "Entry":0.00005081,
    "ExitPreis":0.00006345
  },
  {
    "symbol":"LUNC\/USDT",
    "direction":"Long",
    "indicator":"jma",
    "htf":"12h",
    "param_desc":"ParamA=30.0, ParamB=0.0, ATR=None",
    "entry_time":"2025-12-19T05:00:00+01:00",
    "entry_price":0.00003831,
    "exit_time":"2025-12-21T11:00:00+01:00",
    "exit_price":0.00003998,
    "stake":1000.0,
    "fees":2.0,
    "pnl":41.5917515009,
    "equity_after":15084.8397495533,
    "reason":"Trend flip",
    "size_units":26102845.210127905,
    "Zeit":"2025-12-19T05:00:00+01:00",
    "ExitZeit":"2025-12-21T11:00:00+01:00",
    "Entry":0.00003831,
    "ExitPreis":0.00003998
  },
  {
    "symbol":"LUNC\/USDT",
    "direction":"Long",
    "indicator":"jma",
    "htf":"12h",
    "param_desc":"ParamA=30.0, ParamB=0.0, ATR=None",
    "entry_time":"2025-12-21T17:00:00+01:00",
    "entry_price":0.00004054,
    "exit_time":"2025-12-23T18:00:00+01:00",
    "exit_price":0.00003886,
    "stake":1000.0,
    "fees":2.0,
    "pnl":-43.4405525407,
    "equity_after":15041.3991970126,
    "reason":"Trend flip",
    "size_units":24666995.5599408001,
    "Zeit":"2025-12-21T17:00:00+01:00",
    "ExitZeit":"2025-12-23T18:00:00+01:00",
    "Entry":0.00004054,
    "ExitPreis":0.00003886
  },
  {
    "symbol":"LUNC\/USDT",
    "direction":"Long",
    "indicator":"jma",
    "htf":"12h",
    "param_desc":"ParamA=30.0, ParamB=0.0, ATR=None",
    "entry_time":"2025-12-23T19:00:00+01:00",
    "entry_price":0.00003905,
    "exit_time":"2025-12-25T23:00:00+01:00",
    "exit_price":0.00003993,
    "stake":1000.0,
    "fees":2.0,
    "pnl":20.5352112676,
    "equity_after":15061.9344082802,
    "reason":"Trend flip",
    "size_units":25608194.6222791299,
    "Zeit":"2025-12-23T19:00:00+01:00",
    "ExitZeit":"2025-12-25T23:00:00+01:00",
    "Entry":0.00003905,
    "ExitPreis":0.00003993
  },
  {
    "symbol":"LUNC\/USDT",
    "direction":"Long",
    "indicator":"jma",
    "htf":"12h",
    "param_desc":"ParamA=30.0, ParamB=0.0, ATR=None",
    "entry_time":"2025-12-26T00:00:00+01:00",
    "entry_price":0.00004002,
    "exit_time":"2025-12-28T07:00:00+01:00",
    "exit_price":0.0000408,
    "stake":1000.0,
    "fees":2.0,
    "pnl":17.4902548726,
    "equity_after":15079.4246631527,
    "reason":"Trend flip",
    "size_units":24987506.2468765602,
    "Zeit":"2025-12-26T00:00:00+01:00",
    "ExitZeit":"2025-12-28T07:00:00+01:00",
    "Entry":0.00004002,
    "ExitPreis":0.0000408
  },
  {
    "symbol":"SOL\/EUR",
    "direction":"Long",
    "indicator":"jma",
    "htf":"12h",
    "param_desc":"ParamA=30.0, ParamB=0.0, ATR=None",
    "entry_time":"2025-12-02T22:00:00+01:00",
    "entry_price":119.78,
    "exit_time":"2025-12-05T04:00:00+01:00",
    "exit_price":118.93,
    "stake":1000.0,
    "fees":2.0,
    "pnl":-9.096343296,
    "equity_after":15070.3283198567,
    "reason":"Trend flip",
    "size_units":8.3486391718,
    "Zeit":"2025-12-02T22:00:00+01:00",
    "ExitZeit":"2025-12-05T04:00:00+01:00",
    "Entry":119.78,
    "ExitPreis":118.93
  },
  {
    "symbol":"SOL\/EUR",
    "direction":"Long",
    "indicator":"jma",
    "htf":"12h",
    "param_desc":"ParamA=30.0, ParamB=0.0, ATR=None",
    "entry_time":"2025-12-08T02:00:00+01:00",
    "entry_price":114.51,
    "exit_time":"2025-12-10T08:00:00+01:00",
    "exit_price":119.43,
    "stake":1000.0,
    "fees":2.0,
    "pnl":40.9656798533,
    "equity_after":15111.29399971,
    "reason":"Trend flip",
    "size_units":8.7328617588,
    "Zeit":"2025-12-08T02:00:00+01:00",
    "ExitZeit":"2025-12-10T08:00:00+01:00",
    "Entry":114.51,
    "ExitPreis":119.43
  },
  {
    "symbol":"SOL\/EUR",
    "direction":"Long",
    "indicator":"jma",
    "htf":"12h",
    "param_desc":"ParamA=30.0, ParamB=0.0, ATR=None",
    "entry_time":"2025-12-10T10:00:00+01:00",
    "entry_price":119.38,
    "exit_time":"2025-12-12T14:00:00+01:00",
    "exit_price":118.5,
    "stake":1000.0,
    "fees":2.0,
    "pnl":-9.3714189982,
    "equity_after":15101.9225807118,
    "reason":"Trend flip",
    "size_units":8.3766124979,
    "Zeit":"2025-12-10T10:00:00+01:00",
    "ExitZeit":"2025-12-12T14:00:00+01:00",
    "Entry":119.38,
    "ExitPreis":118.5
  },
  {
    "symbol":"SOL\/EUR",
    "direction":"Long",
    "indicator":"jma",
    "htf":"12h",
    "param_desc":"ParamA=30.0, ParamB=0.0, ATR=None",
    "entry_time":"2025-12-15T01:00:00+01:00",
    "entry_price":110.99,
    "exit_time":"2025-12-17T04:00:00+01:00",
    "exit_price":109.24,
    "stake":1000.0,
    "fees":2.0,
    "pnl":-17.767186233,
    "equity_after":15084.1553944788,
    "reason":"Trend flip",
    "size_units":9.0098207046,
    "Zeit":"2025-12-15T01:00:00+01:00",
    "ExitZeit":"2025-12-17T04:00:00+01:00",
    "Entry":110.99,
    "ExitPreis":109.24
  },
  {
    "symbol":"SOL\/EUR",
    "direction":"Long",
    "indicator":"jma",
    "htf":"12h",
    "param_desc":"ParamA=30.0, ParamB=0.0, ATR=None",
    "entry_time":"2025-12-19T03:00:00+01:00",
    "entry_price":101.44,
    "exit_time":"2025-12-21T08:00:00+01:00",
    "exit_price":106.96,
    "stake":1000.0,
    "fees":2.0,
    "pnl":52.4164037855,
    "equity_after":15136.5717982643,
    "reason":"Trend flip",
    "size_units":9.858044164,
    "Zeit":"2025-12-19T03:00:00+01:00",
    "ExitZeit":"2025-12-21T08:00:00+01:00",
    "Entry":101.44,
    "ExitPreis":106.96
  },
  {
    "symbol":"SOL\/EUR",
    "direction":"Long",
    "indicator":"jma",
    "htf":"12h",
    "param_desc":"ParamA=30.0, ParamB=0.0, ATR=None",
    "entry_time":"2025-12-21T09:00:00+01:00",
    "entry_price":107.22,
    "exit_time":"2025-12-23T13:00:00+01:00",
    "exit_price":105.36,
    "stake":1000.0,
    "fees":2.0,
    "pnl":-19.3475097929,
    "equity_after":15117.2242884714,
    "reason":"Trend flip",
    "size_units":9.3266181683,
    "Zeit":"2025-12-21T09:00:00+01:00",
    "ExitZeit":"2025-12-23T13:00:00+01:00",
    "Entry":107.22,
    "ExitPreis":105.36
  },
  {
    "symbol":"SOL\/EUR",
    "direction":"Long",
    "indicator":"jma",
    "htf":"12h",
    "param_desc":"ParamA=30.0, ParamB=0.0, ATR=None",
    "entry_time":"2025-12-26T03:00:00+01:00",
    "entry_price":104.5,
    "exit_time":"2025-12-28T04:00:00+01:00",
    "exit_price":105.33,
    "stake":1000.0,
    "fees":2.0,
    "pnl":5.9425837321,
    "equity_after":15123.1668722034,
    "reason":"Trend flip",
    "size_units":9.5693779904,
    "Zeit":"2025-12-26T03:00:00+01:00",
    "ExitZeit":"2025-12-28T04:00:00+01:00",
    "Entry":104.5,
    "ExitPreis":105.33
  }
]